{
    "date": "2026-06-18",
    "mode": "confirmed",
    "total_predictions": 8,
    "predictions": [
        {
            "away_team": "Toronto Blue Jays",
            "home_team": "Boston Red Sox",
            "pitchers": {
                "away": {
                    "name": "Trey Yesavage",
                    "hand": "R",
                    "fip": 3.88
                },
                "home": {
                    "name": "Sonny Gray",
                    "hand": "R",
                    "fip": 3.72
                }
            },
            "environment": {
                "venue": "Fenway Park",
                "park_factor": 1.08,
                "weather": {
                    "temp": 77,
                    "wind_mph": 19,
                    "wind_dir": "Out",
                    "wind_lateral": null,
                    "is_indoor": false,
                    "rain_pct": 0,
                    "temp_fatigue_scaler": 1.0,
                    "temp_multiplier": 1.0105,
                    "wind_multiplier": 1.054,
                    "weather_multiplier": 1.0645,
                    "weather_label": "77F | 19 MPH Out | Weather: +6.5%"
                },
                "effective_pf": 1.1497,
                "umpire": {
                    "name": "Manny Gonzalez",
                    "profile": {
                        "games_called": 34.8,
                        "raw_k_mod": 0.9431,
                        "raw_bb_mod": 1.0904,
                        "last_updated": "2026-06-13"
                    }
                }
            },
            "lineups_status": "Confirmed",
            "predictions": {
                "top_down_f5": 5.2,
                "mc_f5": 5.12,
                "mc_f5_away": 2.55,
                "mc_f5_home": 2.56,
                "mc_late": 3.65,
                "mc_full_game": 8.76
            },
            "probabilities": {
                "under_3_5": 0.368,
                "under_4_5": 0.482,
                "under_5_5": 0.596,
                "full_over_7_5": 0.648,
                "full_over_8_5": 0.513,
                "full_over_9_5": 0.382
            },
            "action_matrix": {
                "adv_3_5": "Bet **OVER** (HIGH)",
                "adv_4_5": "Skip",
                "adv_5_5": "Bet **UNDER** (MODERATE)"
            },
            "version": "v3"
        },
        {
            "away_team": "Cleveland Guardians",
            "home_team": "Milwaukee Brewers",
            "pitchers": {
                "away": {
                    "name": "Parker Messick",
                    "hand": "L",
                    "fip": 3.53
                },
                "home": {
                    "name": "Shane Drohan",
                    "hand": "L",
                    "fip": 3.79
                }
            },
            "environment": {
                "venue": "American Family Field",
                "park_factor": 1.0,
                "weather": {
                    "temp": 72,
                    "wind_mph": 11,
                    "wind_dir": "R-L",
                    "wind_lateral": null,
                    "is_indoor": false,
                    "rain_pct": 0,
                    "temp_fatigue_scaler": 1.0,
                    "temp_multiplier": 1.003,
                    "wind_multiplier": 1.0,
                    "weather_multiplier": 1.003,
                    "weather_label": "72F | 11 MPH R-L | Weather: +0.3%"
                },
                "effective_pf": 1.003,
                "umpire": {
                    "name": "Lance Barksdale",
                    "profile": {
                        "games_called": 37.4,
                        "raw_k_mod": 0.9476,
                        "raw_bb_mod": 1.2224,
                        "last_updated": "2026-06-13"
                    }
                }
            },
            "lineups_status": "Confirmed",
            "predictions": {
                "top_down_f5": 4.55,
                "mc_f5": 3.76,
                "mc_f5_away": 1.36,
                "mc_f5_home": 2.4,
                "mc_late": 2.73,
                "mc_full_game": 6.49
            },
            "probabilities": {
                "under_3_5": 0.532,
                "under_4_5": 0.658,
                "under_5_5": 0.761,
                "full_over_7_5": 0.326,
                "full_over_8_5": 0.207,
                "full_over_9_5": 0.122
            },
            "action_matrix": {
                "adv_3_5": "Skip",
                "adv_4_5": "Skip",
                "adv_5_5": "Bet **UNDER** (HIGH)"
            },
            "version": "v3"
        },
        {
            "away_team": "Minnesota Twins",
            "home_team": "Texas Rangers",
            "pitchers": {
                "away": {
                    "name": "Joe Ryan",
                    "hand": "R",
                    "fip": 3.63
                },
                "home": {
                    "name": "Jack Leiter",
                    "hand": "R",
                    "fip": 4.41
                }
            },
            "environment": {
                "venue": "Globe Life Field",
                "park_factor": 1.01,
                "weather": {
                    "temp": 93,
                    "wind_mph": 9,
                    "wind_dir": "L-R",
                    "wind_lateral": null,
                    "is_indoor": false,
                    "rain_pct": 0,
                    "temp_fatigue_scaler": 1.08,
                    "temp_multiplier": 1.0345,
                    "wind_multiplier": 1.0,
                    "weather_multiplier": 1.0345,
                    "weather_label": "93F | 9 MPH L-R | Weather: +3.4%"
                },
                "effective_pf": 1.0448,
                "umpire": {
                    "name": "Mike Estabrook",
                    "profile": {
                        "games_called": 36.7,
                        "raw_k_mod": 1.0394,
                        "raw_bb_mod": 0.9855,
                        "last_updated": "2026-06-13"
                    }
                }
            },
            "lineups_status": "Confirmed",
            "predictions": {
                "top_down_f5": 5.01,
                "mc_f5": 4.57,
                "mc_f5_away": 1.74,
                "mc_f5_home": 2.84,
                "mc_late": 2.61,
                "mc_full_game": 7.19
            },
            "probabilities": {
                "under_3_5": 0.434,
                "under_4_5": 0.556,
                "under_5_5": 0.669,
                "full_over_7_5": 0.429,
                "full_over_8_5": 0.295,
                "full_over_9_5": 0.189
            },
            "action_matrix": {
                "adv_3_5": "Bet **OVER** (MODERATE)",
                "adv_4_5": "Skip",
                "adv_5_5": "Bet **UNDER** (HIGH)"
            },
            "version": "v3"
        },
        {
            "away_team": "Baltimore Orioles",
            "home_team": "Seattle Mariners",
            "pitchers": {
                "away": {
                    "name": "Shane Baz",
                    "hand": "R",
                    "fip": 4.29
                },
                "home": {
                    "name": "Bryan Woo",
                    "hand": "R",
                    "fip": 3.56
                }
            },
            "environment": {
                "venue": "T-Mobile Park",
                "park_factor": 0.92,
                "weather": {
                    "temp": 72,
                    "wind_mph": 9,
                    "wind_dir": "In",
                    "wind_lateral": null,
                    "is_indoor": false,
                    "rain_pct": 0,
                    "temp_fatigue_scaler": 1.0,
                    "temp_multiplier": 1.003,
                    "wind_multiplier": 0.974,
                    "weather_multiplier": 0.977,
                    "weather_label": "72F | 9 MPH In | Weather: -2.3%"
                },
                "effective_pf": 0.8988,
                "umpire": {
                    "name": "Tyler Jones",
                    "profile": {
                        "games_called": 6.3,
                        "raw_k_mod": 0.8929,
                        "raw_bb_mod": 1.1622,
                        "last_updated": "2026-06-13"
                    }
                }
            },
            "lineups_status": "Confirmed",
            "predictions": {
                "top_down_f5": 4.22,
                "mc_f5": 3.82,
                "mc_f5_away": 2.18,
                "mc_f5_home": 1.64,
                "mc_late": 2.53,
                "mc_full_game": 6.35
            },
            "probabilities": {
                "under_3_5": 0.526,
                "under_4_5": 0.648,
                "under_5_5": 0.756,
                "full_over_7_5": 0.305,
                "full_over_8_5": 0.19,
                "full_over_9_5": 0.11
            },
            "action_matrix": {
                "adv_3_5": "Skip",
                "adv_4_5": "Bet **UNDER** (MODERATE)",
                "adv_5_5": "Bet **UNDER** (HIGH)"
            },
            "version": "v3"
        },
        {
            "away_team": "New York Mets",
            "home_team": "Philadelphia Phillies",
            "pitchers": {
                "away": {
                    "name": "Sean Manaea",
                    "hand": "L",
                    "fip": 4.26
                },
                "home": {
                    "name": "Aaron Nola",
                    "hand": "R",
                    "fip": 4.55
                }
            },
            "environment": {
                "venue": "Citizens Bank Park",
                "park_factor": 1.02,
                "weather": {
                    "temp": 91,
                    "wind_mph": 18,
                    "wind_dir": "Out",
                    "wind_lateral": null,
                    "is_indoor": false,
                    "rain_pct": 0,
                    "temp_fatigue_scaler": 1.06,
                    "temp_multiplier": 1.0315,
                    "wind_multiplier": 1.0513,
                    "weather_multiplier": 1.0828,
                    "weather_label": "91F | 18 MPH Out | Weather: +8.3%"
                },
                "effective_pf": 1.1045,
                "umpire": {
                    "name": "Brian Walsh",
                    "profile": {
                        "games_called": 35.6,
                        "raw_k_mod": 0.997,
                        "raw_bb_mod": 1.0247,
                        "last_updated": "2026-06-13"
                    }
                }
            },
            "lineups_status": "Confirmed",
            "predictions": {
                "top_down_f5": 5.69,
                "mc_f5": 5.62,
                "mc_f5_away": 2.51,
                "mc_f5_home": 3.11,
                "mc_late": 3.23,
                "mc_full_game": 8.85
            },
            "probabilities": {
                "under_3_5": 0.301,
                "under_4_5": 0.423,
                "under_5_5": 0.538,
                "full_over_7_5": 0.658,
                "full_over_8_5": 0.524,
                "full_over_9_5": 0.392
            },
            "action_matrix": {
                "adv_3_5": "Bet **OVER** (HIGH)",
                "adv_4_5": "Bet **OVER** (MODERATE)",
                "adv_5_5": "Skip"
            },
            "version": "v3"
        },
        {
            "away_team": "Chicago White Sox",
            "home_team": "New York Yankees",
            "pitchers": {
                "away": {
                    "name": "Bryan Hudson",
                    "hand": "L",
                    "fip": 4.18
                },
                "home": {
                    "name": "Ryan Weathers",
                    "hand": "L",
                    "fip": 4.49
                }
            },
            "environment": {
                "venue": "Yankee Stadium",
                "park_factor": 0.99,
                "weather": {
                    "temp": 90,
                    "wind_mph": 21,
                    "wind_dir": "Out",
                    "wind_lateral": null,
                    "is_indoor": false,
                    "rain_pct": 0,
                    "temp_fatigue_scaler": 1.05,
                    "temp_multiplier": 1.03,
                    "wind_multiplier": 1.0593,
                    "weather_multiplier": 1.0893,
                    "weather_label": "90F | 21 MPH Out | Weather: +8.9%"
                },
                "effective_pf": 1.0784,
                "umpire": {
                    "name": "Gabe Morales",
                    "profile": {
                        "games_called": 37.0,
                        "raw_k_mod": 0.9602,
                        "raw_bb_mod": 0.9683,
                        "last_updated": "2026-06-13"
                    }
                }
            },
            "lineups_status": "Confirmed",
            "predictions": {
                "top_down_f5": 5.83,
                "mc_f5": 5.14,
                "mc_f5_away": 2.56,
                "mc_f5_home": 2.58,
                "mc_late": 3.6,
                "mc_full_game": 8.74
            },
            "probabilities": {
                "under_3_5": 0.362,
                "under_4_5": 0.492,
                "under_5_5": 0.602,
                "full_over_7_5": 0.644,
                "full_over_8_5": 0.509,
                "full_over_9_5": 0.378
            },
            "action_matrix": {
                "adv_3_5": "Bet **OVER** (HIGH)",
                "adv_4_5": "Skip",
                "adv_5_5": "Skip"
            },
            "version": "v3"
        },
        {
            "away_team": "St. Louis Cardinals",
            "home_team": "Kansas City Royals",
            "pitchers": {
                "away": {
                    "name": "Matthew Liberatore",
                    "hand": "L",
                    "fip": 4.39
                },
                "home": {
                    "name": "Noah Cameron",
                    "hand": "L",
                    "fip": 4.07
                }
            },
            "environment": {
                "venue": "Kauffman Stadium",
                "park_factor": 1.05,
                "weather": {
                    "temp": 84,
                    "wind_mph": 7,
                    "wind_dir": "R-L",
                    "wind_lateral": null,
                    "is_indoor": false,
                    "rain_pct": 0,
                    "temp_fatigue_scaler": 1.0,
                    "temp_multiplier": 1.021,
                    "wind_multiplier": 1.0,
                    "weather_multiplier": 1.021,
                    "weather_label": "84F | 7 MPH R-L | Weather: +2.1%"
                },
                "effective_pf": 1.072,
                "umpire": {
                    "name": "Ryan Blakney",
                    "profile": {
                        "games_called": 35.5,
                        "raw_k_mod": 1.004,
                        "raw_bb_mod": 1.0074,
                        "last_updated": "2026-06-13"
                    }
                }
            },
            "lineups_status": "Confirmed",
            "predictions": {
                "top_down_f5": 5.75,
                "mc_f5": 5.05,
                "mc_f5_away": 2.65,
                "mc_f5_home": 2.41,
                "mc_late": 3.38,
                "mc_full_game": 8.44
            },
            "probabilities": {
                "under_3_5": 0.376,
                "under_4_5": 0.493,
                "under_5_5": 0.605,
                "full_over_7_5": 0.607,
                "full_over_8_5": 0.469,
                "full_over_9_5": 0.339
            },
            "action_matrix": {
                "adv_3_5": "Bet **OVER** (HIGH)",
                "adv_4_5": "Skip",
                "adv_5_5": "Skip"
            },
            "version": "v3"
        },
        {
            "away_team": "Los Angeles Angels",
            "home_team": "Athletics",
            "pitchers": {
                "away": {
                    "name": "",
                    "hand": "R",
                    "fip": 4.5
                },
                "home": {
                    "name": "Gage Jump",
                    "hand": "L",
                    "fip": 3.76
                }
            },
            "environment": {
                "venue": "Sutter Health Park",
                "park_factor": 1.0,
                "weather": {
                    "temp": 72,
                    "wind_mph": 0,
                    "wind_dir": "Calm",
                    "wind_lateral": null,
                    "is_indoor": false,
                    "rain_pct": 0,
                    "temp_fatigue_scaler": 1.0,
                    "temp_multiplier": 1.003,
                    "wind_multiplier": 1.0,
                    "weather_multiplier": 1.003,
                    "weather_label": "72F | Calm | Weather: +0.3%"
                },
                "effective_pf": 1.003,
                "umpire": null
            },
            "lineups_status": "Projected (Generic)",
            "predictions": {
                "top_down_f5": 4.97,
                "mc_f5": 4.59,
                "mc_f5_away": 2.69,
                "mc_f5_home": 1.9,
                "mc_late": 3.21,
                "mc_full_game": 7.8
            },
            "probabilities": {
                "under_3_5": 0.425,
                "under_4_5": 0.551,
                "under_5_5": 0.663,
                "full_over_7_5": 0.519,
                "full_over_8_5": 0.38,
                "full_over_9_5": 0.259
            },
            "action_matrix": {
                "adv_3_5": "Bet **OVER** (MODERATE)",
                "adv_4_5": "Skip",
                "adv_5_5": "Bet **UNDER** (HIGH)"
            },
            "version": "v3"
        }
    ]
}