{
    "date": "2026-07-06",
    "mode": "confirmed",
    "total_predictions": 8,
    "predictions": [
        {
            "away_team": "Philadelphia Phillies",
            "home_team": "Kansas City Royals",
            "pitchers": {
                "away": {
                    "name": "Cristopher S\u00e1nchez",
                    "hand": "L",
                    "fip": 2.66
                },
                "home": {
                    "name": "Noah Cameron",
                    "hand": "L",
                    "fip": 4.63
                }
            },
            "environment": {
                "venue": "Kauffman Stadium",
                "park_factor": 1.041,
                "weather": {
                    "temp": 88,
                    "wind_mph": 6,
                    "wind_dir": "In",
                    "wind_lateral": null,
                    "is_indoor": false,
                    "rain_pct": 0,
                    "temp_fatigue_scaler": 1.03,
                    "temp_multiplier": 1.027,
                    "wind_multiplier": 0.986,
                    "weather_multiplier": 1.0126,
                    "weather_label": "88F | 6 MPH In | Weather: +1.3%"
                },
                "effective_pf": 1.0541,
                "umpire": {
                    "name": "Alan Porter",
                    "profile": {
                        "games_called": 23,
                        "raw_k_mod": 0.9851,
                        "raw_bb_mod": 1.0427,
                        "last_updated": "2026-07-06",
                        "game_history_logs": [
                            {
                                "date": "2026-07-02",
                                "k": 10.0,
                                "bb": 6.0,
                                "ip": 18.0,
                                "weight": 0.5
                            }
                        ]
                    }
                }
            },
            "lineups_status": "Confirmed",
            "predictions": {
                "top_down_f5": 4.22,
                "mc_f5": 4.01,
                "mc_f5_away": 2.57,
                "mc_f5_home": 1.44,
                "mc_late": 3.38,
                "mc_full_game": 7.39,
                "td_clamp_applied": false,
                "away_f5_form": {
                    "factor": 1.022,
                    "raw_avg": 2.4,
                    "games_used": 5,
                    "games_raw": [
                        1,
                        3,
                        1,
                        8,
                        2,
                        5
                    ]
                },
                "home_f5_form": {
                    "factor": 0.848,
                    "raw_avg": 1.6,
                    "games_used": 5,
                    "games_raw": [
                        3,
                        1,
                        1,
                        0,
                        3,
                        5
                    ]
                },
                "form_factor": "Not implemented"
            },
            "probabilities": {
                "under_3_5": 0.496,
                "under_4_5": 0.628,
                "under_5_5": 0.736,
                "full_over_7_5": 0.459,
                "full_over_8_5": 0.322,
                "full_over_9_5": 0.211
            },
            "action_matrix": {
                "adv_3_5": "Skip",
                "adv_4_5": "Bet **UNDER** (MODERATE)",
                "adv_5_5": "Bet **UNDER** (HIGH)"
            },
            "version": "v4",
            "gatekeeper_logic": {
                "category": "High-Confidence",
                "action": "BET F5 UNDER",
                "reason": "Engine Convergence: Models perfectly aligned with measurable market edge.",
                "odds": 1.85
            }
        },
        {
            "away_team": "New York Yankees",
            "home_team": "Tampa Bay Rays",
            "pitchers": {
                "away": {
                    "name": "Cam Schlittler",
                    "hand": "R",
                    "fip": 2.88
                },
                "home": {
                    "name": "Griffin Jax",
                    "hand": "R",
                    "fip": 3.72
                }
            },
            "environment": {
                "venue": "Tropicana Field",
                "park_factor": 0.959,
                "weather": {
                    "temp": 72,
                    "wind_mph": 0,
                    "wind_dir": "Indoor",
                    "wind_lateral": null,
                    "is_indoor": true,
                    "rain_pct": 0,
                    "temp_fatigue_scaler": 1.0,
                    "temp_multiplier": 1.0,
                    "wind_multiplier": 1.0,
                    "weather_multiplier": 1.0,
                    "weather_label": "Indoor / Roof Closed | No weather adjustment"
                },
                "effective_pf": 0.959,
                "umpire": {
                    "name": "Emil Jimenez",
                    "profile": {
                        "games_called": 22,
                        "raw_k_mod": 0.9956,
                        "raw_bb_mod": 1.0133,
                        "last_updated": "2026-07-06",
                        "game_history_logs": []
                    }
                }
            },
            "lineups_status": "Confirmed",
            "predictions": {
                "top_down_f5": 3.82,
                "mc_f5": 3.8,
                "mc_f5_away": 1.94,
                "mc_f5_home": 1.86,
                "mc_late": 2.88,
                "mc_full_game": 6.68,
                "td_clamp_applied": false,
                "away_f5_form": {
                    "factor": 0.775,
                    "raw_avg": 0.8,
                    "games_used": 5,
                    "games_raw": [
                        0,
                        4,
                        3,
                        0,
                        1,
                        0
                    ]
                },
                "home_f5_form": {
                    "factor": 1.109,
                    "raw_avg": 2.8,
                    "games_used": 5,
                    "games_raw": [
                        0,
                        7,
                        0,
                        5,
                        2,
                        8
                    ]
                },
                "form_factor": "Not implemented"
            },
            "probabilities": {
                "under_3_5": 0.525,
                "under_4_5": 0.65,
                "under_5_5": 0.751,
                "full_over_7_5": 0.353,
                "full_over_8_5": 0.23,
                "full_over_9_5": 0.138
            },
            "action_matrix": {
                "adv_3_5": "Skip",
                "adv_4_5": "Bet **UNDER** (HIGH)",
                "adv_5_5": "Bet **UNDER** (HIGH)"
            },
            "version": "v4",
            "gatekeeper_logic": {
                "category": "High-Confidence",
                "action": "BET F5 UNDER",
                "reason": "Engine Convergence: Models perfectly aligned with measurable market edge.",
                "odds": 1.85
            }
        },
        {
            "away_team": "Houston Astros",
            "home_team": "Washington Nationals",
            "pitchers": {
                "away": {
                    "name": "Mike Burrows",
                    "hand": "R",
                    "fip": 4.81
                },
                "home": {
                    "name": "Miles Mikolas",
                    "hand": "R",
                    "fip": 6.19
                }
            },
            "environment": {
                "venue": "Nationals Park",
                "park_factor": 1.074,
                "weather": {
                    "temp": 85,
                    "wind_mph": 7,
                    "wind_dir": "In",
                    "wind_lateral": null,
                    "is_indoor": false,
                    "rain_pct": 58,
                    "temp_fatigue_scaler": 1.0,
                    "temp_multiplier": 1.0225,
                    "wind_multiplier": 0.982,
                    "weather_multiplier": 1.0041,
                    "weather_label": "85F | 7 MPH In | Weather: +0.4%"
                },
                "effective_pf": 1.0784,
                "umpire": {
                    "name": "Dan Merzel",
                    "profile": {
                        "games_called": 23,
                        "raw_k_mod": 0.9799,
                        "raw_bb_mod": 0.9689,
                        "last_updated": "2026-07-06",
                        "game_history_logs": [
                            {
                                "date": "2026-07-02",
                                "k": 20.0,
                                "bb": 5.0,
                                "ip": 18.0,
                                "weight": 0.5
                            }
                        ]
                    }
                }
            },
            "lineups_status": "Confirmed",
            "predictions": {
                "top_down_f5": 5.9,
                "mc_f5": 5.96,
                "mc_f5_away": 2.79,
                "mc_f5_home": 3.17,
                "mc_late": 3.69,
                "mc_full_game": 9.65,
                "td_clamp_applied": false,
                "away_f5_form": {
                    "factor": 0.848,
                    "raw_avg": 1.6,
                    "games_used": 5,
                    "games_raw": [
                        1,
                        5,
                        0,
                        1,
                        6,
                        1
                    ]
                },
                "home_f5_form": {
                    "factor": 1.022,
                    "raw_avg": 2.4,
                    "games_used": 5,
                    "games_raw": [
                        4,
                        1,
                        5,
                        7,
                        1,
                        1
                    ]
                },
                "form_factor": "Not implemented"
            },
            "probabilities": {
                "under_3_5": 0.286,
                "under_4_5": 0.4,
                "under_5_5": 0.511,
                "full_over_7_5": 0.747,
                "full_over_8_5": 0.627,
                "full_over_9_5": 0.498
            },
            "action_matrix": {
                "adv_3_5": "Skip (Team Bias Veto - Realized Hitter Edge)",
                "adv_4_5": "Skip (Team Bias Veto - Realized Hitter Edge)",
                "adv_5_5": "Skip"
            },
            "version": "v4",
            "gatekeeper_logic": {
                "category": "High-Confidence",
                "action": "BET F5 OVER",
                "reason": "Engine Convergence: Models perfectly aligned with measurable market edge.",
                "odds": 1.85
            }
        },
        {
            "away_team": "New York Mets",
            "home_team": "Atlanta Braves",
            "pitchers": {
                "away": {
                    "name": "Freddy Peralta",
                    "hand": "R",
                    "fip": 4.24
                },
                "home": {
                    "name": "Reynaldo L\u00f3pez",
                    "hand": "R",
                    "fip": 5.01
                }
            },
            "environment": {
                "venue": "Truist Park",
                "park_factor": 0.967,
                "weather": {
                    "temp": 84,
                    "wind_mph": 8,
                    "wind_dir": "Out",
                    "wind_lateral": null,
                    "is_indoor": false,
                    "rain_pct": 0,
                    "temp_fatigue_scaler": 1.0,
                    "temp_multiplier": 1.021,
                    "wind_multiplier": 1.022,
                    "weather_multiplier": 1.0435,
                    "weather_label": "84F | 8 MPH Out | Weather: +4.4%"
                },
                "effective_pf": 1.0091,
                "umpire": {
                    "name": "Lance Barrett",
                    "profile": {
                        "games_called": 24,
                        "raw_k_mod": 0.9338,
                        "raw_bb_mod": 1.0305,
                        "last_updated": "2026-07-06",
                        "game_history_logs": [
                            {
                                "date": "2026-07-01",
                                "k": 22.0,
                                "bb": 6.0,
                                "ip": 22.0,
                                "weight": 0.5
                            }
                        ]
                    }
                }
            },
            "lineups_status": "Confirmed",
            "predictions": {
                "top_down_f5": 4.82,
                "mc_f5": 5.34,
                "mc_f5_away": 2.95,
                "mc_f5_home": 2.39,
                "mc_late": 2.84,
                "mc_full_game": 8.18,
                "td_clamp_applied": false,
                "away_f5_form": {
                    "factor": 0.775,
                    "raw_avg": 0.8,
                    "games_used": 5,
                    "games_raw": [
                        5,
                        1,
                        2,
                        0,
                        1,
                        0
                    ]
                },
                "home_f5_form": {
                    "factor": 1.152,
                    "raw_avg": 3.0,
                    "games_used": 5,
                    "games_raw": [
                        3,
                        6,
                        4,
                        5,
                        2,
                        1
                    ]
                },
                "form_factor": "Not implemented"
            },
            "probabilities": {
                "under_3_5": 0.348,
                "under_4_5": 0.467,
                "under_5_5": 0.58,
                "full_over_7_5": 0.571,
                "full_over_8_5": 0.432,
                "full_over_9_5": 0.306
            },
            "action_matrix": {
                "adv_3_5": "Bet **OVER** (HIGH)",
                "adv_4_5": "Bet **OVER** (MODERATE)",
                "adv_5_5": "Bet **UNDER** (HIGH)"
            },
            "version": "v4",
            "gatekeeper_logic": {
                "category": "High-Value Strategy",
                "action": "BET F5 OVER",
                "reason": "Divergent baseline alignment confirms line value. Trusting MC via pure distance edge.",
                "odds": 1.85
            }
        },
        {
            "away_team": "Milwaukee Brewers",
            "home_team": "St. Louis Cardinals",
            "pitchers": {
                "away": {
                    "name": "Shane Drohan",
                    "hand": "L",
                    "fip": 4.57
                },
                "home": {
                    "name": "Dustin May",
                    "hand": "R",
                    "fip": 4.15
                }
            },
            "environment": {
                "venue": "Busch Stadium",
                "park_factor": 0.917,
                "weather": {
                    "temp": 84,
                    "wind_mph": 9,
                    "wind_dir": "In",
                    "wind_lateral": null,
                    "is_indoor": false,
                    "rain_pct": 0,
                    "temp_fatigue_scaler": 1.0,
                    "temp_multiplier": 1.021,
                    "wind_multiplier": 0.974,
                    "weather_multiplier": 0.9945,
                    "weather_label": "84F | 9 MPH In | Weather: -0.5%"
                },
                "effective_pf": 0.912,
                "umpire": {
                    "name": "Todd Tichenor",
                    "profile": {
                        "games_called": 23,
                        "raw_k_mod": 0.9292,
                        "raw_bb_mod": 0.9341,
                        "last_updated": "2026-07-06",
                        "game_history_logs": []
                    }
                }
            },
            "lineups_status": "Projected (Generic)",
            "predictions": {
                "top_down_f5": 4.18,
                "mc_f5": 3.95,
                "mc_f5_away": 2.11,
                "mc_f5_home": 1.84,
                "mc_late": 2.91,
                "mc_full_game": 6.86,
                "td_clamp_applied": false,
                "away_f5_form": {
                    "factor": 0.848,
                    "raw_avg": 1.6,
                    "games_used": 5,
                    "games_raw": [
                        0,
                        2,
                        3,
                        1,
                        2,
                        6
                    ]
                },
                "home_f5_form": {
                    "factor": 0.935,
                    "raw_avg": 2.0,
                    "games_used": 5,
                    "games_raw": [
                        0,
                        2,
                        14,
                        3,
                        1,
                        4
                    ]
                },
                "form_factor": "Not implemented"
            },
            "probabilities": {
                "under_3_5": 0.498,
                "under_4_5": 0.63,
                "under_5_5": 0.737,
                "full_over_7_5": 0.381,
                "full_over_8_5": 0.253,
                "full_over_9_5": 0.156
            },
            "action_matrix": {
                "adv_3_5": "Skip",
                "adv_4_5": "Bet **UNDER** (HIGH)",
                "adv_5_5": "Bet **UNDER** (HIGH)"
            },
            "version": "v4",
            "gatekeeper_logic": {
                "category": "High-Confidence",
                "action": "BET F5 UNDER",
                "reason": "Engine Convergence: Models perfectly aligned with measurable market edge.",
                "odds": 1.85
            }
        },
        {
            "away_team": "Arizona Diamondbacks",
            "home_team": "San Diego Padres",
            "pitchers": {
                "away": {
                    "name": "Brandon Pfaadt",
                    "hand": "R",
                    "fip": 5.08
                },
                "home": {
                    "name": "Walker Buehler",
                    "hand": "R",
                    "fip": 3.97
                }
            },
            "environment": {
                "venue": "Petco Park",
                "park_factor": 0.894,
                "weather": {
                    "temp": 73,
                    "wind_mph": 11,
                    "wind_dir": "Out",
                    "wind_lateral": null,
                    "is_indoor": false,
                    "rain_pct": 0,
                    "temp_fatigue_scaler": 1.0,
                    "temp_multiplier": 1.0045,
                    "wind_multiplier": 1.0327,
                    "weather_multiplier": 1.0373,
                    "weather_label": "73F | 11 MPH Out | Weather: +3.7%"
                },
                "effective_pf": 0.9273,
                "umpire": null
            },
            "lineups_status": "Projected (Generic)",
            "predictions": {
                "top_down_f5": 4.53,
                "mc_f5": 4.88,
                "mc_f5_away": 2.37,
                "mc_f5_home": 2.51,
                "mc_late": 2.78,
                "mc_full_game": 7.66,
                "td_clamp_applied": false,
                "away_f5_form": {
                    "factor": 0.978,
                    "raw_avg": 2.2,
                    "games_used": 5,
                    "games_raw": [
                        1,
                        3,
                        3,
                        0,
                        6,
                        4
                    ]
                },
                "home_f5_form": {
                    "factor": 0.848,
                    "raw_avg": 1.6,
                    "games_used": 5,
                    "games_raw": [
                        1,
                        0,
                        2,
                        6,
                        2,
                        3
                    ]
                },
                "form_factor": "Not implemented"
            },
            "probabilities": {
                "under_3_5": 0.391,
                "under_4_5": 0.515,
                "under_5_5": 0.627,
                "full_over_7_5": 0.499,
                "full_over_8_5": 0.36,
                "full_over_9_5": 0.242
            },
            "action_matrix": {
                "adv_3_5": "Bet **OVER** (HIGH)",
                "adv_4_5": "Skip",
                "adv_5_5": "Bet **UNDER** (HIGH)"
            },
            "version": "v4",
            "gatekeeper_logic": {
                "category": "No Edge",
                "reason": "Did not meet divergence thresholds."
            }
        },
        {
            "away_team": "Toronto Blue Jays",
            "home_team": "San Francisco Giants",
            "pitchers": {
                "away": {
                    "name": "Kevin Gausman",
                    "hand": "R",
                    "fip": 2.99
                },
                "home": {
                    "name": "Landen Roupp",
                    "hand": "R",
                    "fip": 3.02
                }
            },
            "environment": {
                "venue": "Oracle Park",
                "park_factor": 0.94,
                "weather": {
                    "temp": 64,
                    "wind_mph": 10,
                    "wind_dir": "Out",
                    "wind_lateral": null,
                    "is_indoor": false,
                    "rain_pct": 0,
                    "temp_fatigue_scaler": 0.996,
                    "temp_multiplier": 0.9985,
                    "wind_multiplier": 1.03,
                    "weather_multiplier": 1.0285,
                    "weather_label": "64F | 10 MPH Out | Weather: +2.8%"
                },
                "effective_pf": 0.9668,
                "umpire": null
            },
            "lineups_status": "Projected (Generic)",
            "predictions": {
                "top_down_f5": 4.16,
                "mc_f5": 4.01,
                "mc_f5_away": 2.01,
                "mc_f5_home": 2.01,
                "mc_late": 2.96,
                "mc_full_game": 6.98,
                "td_clamp_applied": false,
                "away_f5_form": {
                    "factor": 0.775,
                    "raw_avg": 0.8,
                    "games_used": 5,
                    "games_raw": [
                        0,
                        0,
                        2,
                        5,
                        0,
                        2
                    ]
                },
                "home_f5_form": {
                    "factor": 0.978,
                    "raw_avg": 2.2,
                    "games_used": 5,
                    "games_raw": [
                        5,
                        6,
                        2,
                        3,
                        0,
                        1
                    ]
                },
                "form_factor": "Not implemented"
            },
            "probabilities": {
                "under_3_5": 0.502,
                "under_4_5": 0.624,
                "under_5_5": 0.732,
                "full_over_7_5": 0.398,
                "full_over_8_5": 0.268,
                "full_over_9_5": 0.167
            },
            "action_matrix": {
                "adv_3_5": "Skip",
                "adv_4_5": "Bet **UNDER** (HIGH)",
                "adv_5_5": "Bet **UNDER** (HIGH)"
            },
            "version": "v4",
            "gatekeeper_logic": {
                "category": "High-Confidence",
                "action": "BET F5 UNDER",
                "reason": "Engine Convergence: Models perfectly aligned with measurable market edge.",
                "odds": 1.85
            }
        },
        {
            "away_team": "Colorado Rockies",
            "home_team": "Los Angeles Dodgers",
            "pitchers": {
                "away": {
                    "name": "Kyle Freeland",
                    "hand": "L",
                    "fip": 4.67
                },
                "home": {
                    "name": "Eric Lauer",
                    "hand": "L",
                    "fip": 6.04
                }
            },
            "environment": {
                "venue": "UNIQLO Field at Dodger Stadium",
                "park_factor": 0.949,
                "weather": {
                    "temp": 77,
                    "wind_mph": 9,
                    "wind_dir": "Out",
                    "wind_lateral": null,
                    "is_indoor": false,
                    "rain_pct": 0,
                    "temp_fatigue_scaler": 1.0,
                    "temp_multiplier": 1.0105,
                    "wind_multiplier": 1.026,
                    "weather_multiplier": 1.0368,
                    "weather_label": "77F | 9 MPH Out | Weather: +3.7%"
                },
                "effective_pf": 0.9839,
                "umpire": {
                    "name": "Dan Iassogna",
                    "profile": {
                        "games_called": 24,
                        "raw_k_mod": 0.9991,
                        "raw_bb_mod": 1.105,
                        "last_updated": "2026-07-06",
                        "game_history_logs": [
                            {
                                "date": "2026-07-01",
                                "k": 17.0,
                                "bb": 10.0,
                                "ip": 17.0,
                                "weight": 0.5
                            }
                        ]
                    }
                }
            },
            "lineups_status": "Confirmed",
            "predictions": {
                "top_down_f5": 5.1,
                "mc_f5": 4.85,
                "mc_f5_away": 2.12,
                "mc_f5_home": 2.73,
                "mc_late": 2.95,
                "mc_full_game": 7.8,
                "td_clamp_applied": false,
                "away_f5_form": {
                    "factor": 1.225,
                    "raw_avg": 3.6,
                    "games_used": 5,
                    "games_raw": [
                        4,
                        3,
                        14,
                        5,
                        5,
                        1
                    ]
                },
                "home_f5_form": {
                    "factor": 0.804,
                    "raw_avg": 1.4,
                    "games_used": 5,
                    "games_raw": [
                        0,
                        1,
                        0,
                        10,
                        1,
                        5
                    ]
                },
                "form_factor": "Not implemented"
            },
            "probabilities": {
                "under_3_5": 0.396,
                "under_4_5": 0.526,
                "under_5_5": 0.631,
                "full_over_7_5": 0.518,
                "full_over_8_5": 0.379,
                "full_over_9_5": 0.258
            },
            "action_matrix": {
                "adv_3_5": "Bet **OVER** (HIGH)",
                "adv_4_5": "Skip",
                "adv_5_5": "Bet **UNDER** (HIGH)"
            },
            "version": "v4",
            "gatekeeper_logic": {
                "category": "No Edge",
                "reason": "Did not meet divergence thresholds."
            }
        }
    ]
}